notes/argument_parsing.rst
notes/readme.txt
notes/traversing_client_data.rst
suds/__init__.py
suds/argparser.py
suds/builder.py
suds/cache.py
suds/client.py
suds/metrics.py
suds/options.py
suds/plugin.py
suds/properties.py
suds/reader.py
suds/resolver.py
suds/servicedefinition.py
suds/serviceproxy.py
suds/soaparray.py
suds/store.py
suds/sudsobject.py
suds/wsdl.py
suds/wsse.py
suds/bindings/__init__.py
suds/bindings/binding.py
suds/bindings/document.py
suds/bindings/multiref.py
suds/bindings/rpc.py
suds/mx/__init__.py
suds/mx/appender.py
suds/mx/basic.py
suds/mx/core.py
suds/mx/encoded.py
suds/mx/literal.py
suds/mx/typer.py
suds/sax/__init__.py
suds/sax/attribute.py
suds/sax/date.py
suds/sax/document.py
suds/sax/element.py
suds/sax/enc.py
suds/sax/parser.py
suds/sax/text.py
suds/transport/__init__.py
suds/transport/http.py
suds/transport/https.py
suds/transport/options.py
suds/umx/__init__.py
suds/umx/attrlist.py
suds/umx/basic.py
suds/umx/core.py
suds/umx/encoded.py
suds/umx/typed.py
suds/xsd/__init__.py
suds/xsd/deplist.py
suds/xsd/doctor.py
suds/xsd/query.py
suds/xsd/schema.py
suds/xsd/sxbase.py
suds/xsd/sxbasic.py
suds/xsd/sxbuiltin.py
suds_bis-1.0.1.dist-info/LICENSE
suds_bis-1.0.1.dist-info/METADATA
suds_bis-1.0.1.dist-info/WHEEL
suds_bis-1.0.1.dist-info/top_level.txt
suds_bis-1.0.1.dist-info/RECORD
